Metadata-Version: 2.1
Name: speakWin-2
Version: 0.0.2
Summary: Text to Speech Windows Based.
Author-email: nayakdebasish7205@gmail.com
